example.py
example_backstage.py
setup.py
tornado_measures/__init__.py
tornado_measures.egg-info/PKG-INFO
tornado_measures.egg-info/SOURCES.txt
tornado_measures.egg-info/dependency_links.txt
tornado_measures.egg-info/requires.txt
tornado_measures.egg-info/top_level.txt
tornado_measures.egg-info/zip-safe