Metadata-Version: 1.1
Name: tornado-measures
Version: 1.0.2
Summary: Simple Tornado HTTP Client that automatically sends http response metrics to Backstage measures
Home-page: http://github.com/globocom/tornado-measures
Author: Globo.com
Author-email: backstage1@corp.globo.com
License: MIT
Platform: UNKNOWN
Classifier: Development Status :: 5 - Production/Stable
Classifier: Environment :: Web Environment
Classifier: Intended Audience :: Developers
Classifier: Operating System :: OS Independent
Classifier: Programming Language :: Python
